apidoc_to_openapi/__init__.py
apidoc_to_openapi/lib/__init__.py
apidoc_to_openapi/lib/errors.py
apidoc_to_openapi/lib/helper_methods.py
apidoc_to_openapi/lib/input_files.py
apidoc_to_openapi/lib/log.py
apidoc_to_openapi/lib/openapi_builder.py
apidoc_to_openapi/lib/parse_config.py
apidoc_to_openapi/lib/annotations/__init__.py
apidoc_to_openapi/lib/annotations/api.py
apidoc_to_openapi/lib/annotations/api_group.py
apidoc_to_openapi/lib/annotations/api_name.py
apidoc_to_openapi/lib/annotations/api_param.py
apidoc_to_openapi/lib/annotations/api_success.py
apidoc_to_openapi/lib/annotations/apidoc_annotation.py
apidoc_to_openapi-0.0.2.data/scripts/apidoc-to-openapi
tests/__init__.py
tests/api_group_test.py
tests/api_name_test.py
tests/api_param_test.py
tests/api_success_test.py
tests/api_test.py
apidoc_to_openapi-0.0.2.dist-info/LICENSE.md
apidoc_to_openapi-0.0.2.dist-info/METADATA
apidoc_to_openapi-0.0.2.dist-info/WHEEL
apidoc_to_openapi-0.0.2.dist-info/top_level.txt
apidoc_to_openapi-0.0.2.dist-info/RECORD
