Metadata-Version: 2.1
Name: apidoc-to-openapi
Version: 0.0.2
Summary: A python package which converts apidoc comments in various languages to OpenApi Spec .json files.
Home-page: https://github.com/GrahamMThomas/apidoc_to_openapi
Author: Graham Thomas
Author-email: grahamthethomas@gmail.com
License: UNKNOWN
Platform: UNKNOWN
Classifier: Programming Language :: Python :: 3
Classifier: License :: OSI Approved :: MIT License
Classifier: Operating System :: OS Independent
Requires-Python: >=3.6
Requires-Dist: colorama
Requires-Dist: pyyaml
